pylaugh/__init__.py
pylaugh/humor.py
pylaugh-0.3.1.dist-info/licenses/LICENSE.txt
pylaugh-0.3.1.dist-info/METADATA
pylaugh-0.3.1.dist-info/WHEEL
pylaugh-0.3.1.dist-info/top_level.txt
pylaugh-0.3.1.dist-info/RECORD
