Metadata-Version: 2.4
Name: pylaugh
Version: 0.3.1
Summary: A Python module that delivers programming jokes and puns!
Author: Vibhor Kedia
Author-email: vibhorkedia21@gmail.com
License: MIT
Classifier: Programming Language :: Python :: 3
Classifier: License :: OSI Approved :: MIT License
Classifier: Operating System :: OS Independent
License-File: LICENSE.txt
Dynamic: author
Dynamic: author-email
Dynamic: classifier
Dynamic: description
Dynamic: description-content-type
Dynamic: license
Dynamic: license-file
Dynamic: summary
